tskit_book_theme/__init__.py
tskit_book_theme/_compile_translations.py
tskit_book_theme/_transforms.py
tskit_book_theme/assets/scripts/index.js
tskit_book_theme/assets/styles/abstracts/_mixins.scss
tskit_book_theme/assets/styles/abstracts/_variables.scss
tskit_book_theme/assets/styles/base/_base.scss
tskit_book_theme/assets/styles/base/_print.scss
tskit_book_theme/assets/styles/base/_typography.scss
tskit_book_theme/assets/styles/components/_icon-links.scss
tskit_book_theme/assets/styles/components/_logo.scss
tskit_book_theme/assets/styles/components/_search.scss
tskit_book_theme/assets/styles/content/_code.scss
tskit_book_theme/assets/styles/content/_images.scss
tskit_book_theme/assets/styles/content/_margin.scss
tskit_book_theme/assets/styles/content/_notebooks.scss
tskit_book_theme/assets/styles/content/_quotes.scss
tskit_book_theme/assets/styles/extensions/_comments.scss
tskit_book_theme/assets/styles/extensions/_thebe.scss
tskit_book_theme/assets/styles/index.scss
tskit_book_theme/assets/styles/sections/_announcement.scss
tskit_book_theme/assets/styles/sections/_article-container.scss
tskit_book_theme/assets/styles/sections/_article.scss
tskit_book_theme/assets/styles/sections/_footer-article.scss
tskit_book_theme/assets/styles/sections/_footer-content.scss
tskit_book_theme/assets/styles/sections/_header-article.scss
tskit_book_theme/assets/styles/sections/_header-primary.scss
tskit_book_theme/assets/styles/sections/_sidebar-primary.scss
tskit_book_theme/assets/styles/sections/_sidebar-secondary.scss
tskit_book_theme/assets/styles/tskit/_palette.scss
tskit_book_theme/assets/styles/tskit/_tskit.scss
tskit_book_theme/assets/translations/README.md
tskit_book_theme/assets/translations/jsons/By the.json
tskit_book_theme/assets/translations/jsons/By.json
tskit_book_theme/assets/translations/jsons/Contents.json
tskit_book_theme/assets/translations/jsons/Copyright.json
tskit_book_theme/assets/translations/jsons/Download notebook file.json
tskit_book_theme-1.0.1.dist-info/LICENSE
tskit_book_theme-1.0.1.dist-info/METADATA
tskit_book_theme-1.0.1.dist-info/WHEEL
tskit_book_theme-1.0.1.dist-info/entry_points.txt
tskit_book_theme-1.0.1.dist-info/RECORD